pytest_dsl_ssh/__init__.py
pytest_dsl_ssh/core/__init__.py
pytest_dsl_ssh/core/config_manager.py
pytest_dsl_ssh/core/connection_pool.py
pytest_dsl_ssh/core/sftp_client.py
pytest_dsl_ssh/core/ssh_client.py
pytest_dsl_ssh/core/unified_config.py
pytest_dsl_ssh/exceptions/__init__.py
pytest_dsl_ssh/keywords/__init__.py
pytest_dsl_ssh/keywords/sftp_keywords.py
pytest_dsl_ssh/keywords/ssh_keywords.py
pytest_dsl_ssh-0.1.2.dist-info/METADATA
pytest_dsl_ssh-0.1.2.dist-info/WHEEL
pytest_dsl_ssh-0.1.2.dist-info/entry_points.txt
pytest_dsl_ssh-0.1.2.dist-info/RECORD
