Metadata-Version: 2.4
Name: pytest-dsl-ssh
Version: 0.1.2
Summary: SSH/SFTP关键字插件，为pytest-dsl提供SSH和SFTP操作能力
Project-URL: Homepage, https://github.com/pytest-dsl/pytest-dsl-ssh
Project-URL: Documentation, https://pytest-dsl.vercel.app/
Project-URL: Repository, https://github.com/pytest-dsl/pytest-dsl-ssh.git
Project-URL: Bug Tracker, https://github.com/pytest-dsl/pytest-dsl-ssh/issues
Author-email: pytest-dsl团队 <pytest.dsl@example.com>
License-Expression: MIT
Classifier: Development Status :: 4 - Beta
Classifier: Intended Audience :: Developers
Classifier: License :: OSI Approved :: MIT License
Classifier: Programming Language :: Python :: 3
Classifier: Programming Language :: Python :: 3.9
Classifier: Programming Language :: Python :: 3.10
Classifier: Programming Language :: Python :: 3.11
Classifier: Programming Language :: Python :: 3.12
Classifier: Topic :: Software Development :: Testing
Classifier: Topic :: System :: Networking
Requires-Python: >=3.9
Requires-Dist: paramiko>=3.0.0
Requires-Dist: pytest-dsl>=0.16.1
Requires-Dist: pytest>=7.0.0
Requires-Dist: pyyaml>=6.0
Provides-Extra: dev
Requires-Dist: black>=23.0.0; extra == 'dev'
Requires-Dist: flake8>=6.0.0; extra == 'dev'
Requires-Dist: mypy>=1.0.0; extra == 'dev'
Requires-Dist: pre-commit>=3.0.0; extra == 'dev'
Requires-Dist: pytest-cov>=4.0.0; extra == 'dev'
Provides-Extra: test
Requires-Dist: docker>=6.0.0; extra == 'test'
Requires-Dist: pytest-asyncio>=0.21.0; extra == 'test'
Requires-Dist: pytest-mock>=3.10.0; extra == 'test'
